manygo/__init__.py
manygo/py.typed
manygo-0.2.0.dist-info/METADATA
manygo-0.2.0.dist-info/WHEEL
manygo-0.2.0.dist-info/licenses/LICENSE
manygo-0.2.0.dist-info/RECORD
