Metadata-Version: 2.4
Name: manygo
Version: 0.2.0
Summary: Python library with helpers for packaging golang source code
Project-URL: Repository, https://github.com/jmelahman/manygo
Author-email: Jamison Lahman <jamison@lahman.dev>
License-Expression: MIT
License-File: LICENSE
Keywords: golang,packaging,platform-tags
Classifier: Development Status :: 3 - Alpha
Classifier: Intended Audience :: Developers
Classifier: License :: OSI Approved :: MIT License
Classifier: Programming Language :: Python :: 3
Classifier: Programming Language :: Python :: 3.9
Classifier: Programming Language :: Python :: 3.10
Classifier: Programming Language :: Python :: 3.11
Classifier: Programming Language :: Python :: 3.12
Classifier: Programming Language :: Python :: 3.13
Classifier: Typing :: Typed
Requires-Python: >=3.10
